conflog/__init__.py
conflog/config.py
conflog/handlers/__init__.py
conflog/handlers/file_handler.py
conflog/handlers/stream_handler.py
conflog/loaders/__init__.py
conflog/loaders/environ_loader.py
conflog/loaders/ini_loader.py
conflog/loaders/json_loader.py
conflog/loaders/xml_loader.py
conflog/loaders/yaml_loader.py
conflog-2.0.1.dist-info/LICENSE
conflog-2.0.1.dist-info/METADATA
conflog-2.0.1.dist-info/WHEEL
conflog-2.0.1.dist-info/entry_points.txt
conflog-2.0.1.dist-info/RECORD
