Metadata-Version: 2.1
Name: conflog
Version: 2.0.1
Summary: Python logging setup via environment variables and configuration files
Home-page: https://github.com/cliffano/pyconflog
License: Apache-2.0
Keywords: log,logger,logging,config,configuration,environment,envvar
Author: Cliffano Subagio
Author-email: cliffano@gmail.com
Requires-Python: >=3.10,<4.0
Classifier: License :: OSI Approved :: Apache Software License
Classifier: Operating System :: OS Independent
Classifier: Programming Language :: Python :: 3
Classifier: Programming Language :: Python :: 3.10
Classifier: Programming Language :: Python :: 3.11
Classifier: Programming Language :: Python :: 3.12
Classifier: Programming Language :: Python :: 3.13
Requires-Dist: PyYAML (>=6.0.2,<7.0.0)
Requires-Dist: toml (>=0.10.2,<0.11.0)
Project-URL: Documentation, https://github.com/cliffano/pyconflog
Project-URL: Repository, https://github.com/cliffano/pyconflog
